{
  "_id": "G3DBfWSgnqowPgz3",
  "name": "Come from Money",
  "type": "trait",
  "system": {
    "summary": "",
    "description": "Your family may demand you do something for them or interfere with you pursuing your career",
    "cost": 0
  },
  "flags": {
    "srx": {
      "catalogType": "trait",
      "catalogData": {
        "name": "Come from Money",
        "srxId": 10515,
        "type": "Trait",
        "type2": null,
        "description": "Your family may demand you do something for them or interfere with you pursuing your career",
        "options": [],
        "slug": "come-from-money"
      }
    }
  },
  "effects": [],
  "folder": "WwCjT3cWh1ZOvZmE",
  "sort": 0,
  "ownership": {
    "default": 0
  },
  "_key": "!items!G3DBfWSgnqowPgz3"
}