{
  "_id": "EKXr0UfbtMgeTumu",
  "name": "Biofeedback Filter",
  "type": "gear",
  "system": {
    "summary": "Software Talents",
    "description": "",
    "subtype": "Utility",
    "rating": 0,
    "quantity": 1,
    "cost": 12000
  },
  "flags": {
    "srx": {
      "catalogType": "gear",
      "catalogData": {
        "name": "Biofeedback Filter",
        "srxId": 6051,
        "category": "Software Talents",
        "cost": 12000,
        "properties": [],
        "options": [],
        "type": "Utility",
        "type2": "Software",
        "maxRating": null,
        "ratingSquared": false,
        "uniqueScale": null,
        "uniqueNuyenScale": [],
        "capacity": 0,
        "enhancementType": null,
        "matrix": {
          "dataProcessing": "",
          "firewall": "",
          "hotSimFirewall": "",
          "hackingTests": "",
          "agents": "",
          "rank": "",
          "modCapacity": ""
        },
        "installedEnhancements": [],
        "slug": "biofeedback-filter"
      }
    }
  },
  "effects": [],
  "folder": "pbbeO4rnhMi0QcIf",
  "sort": 0,
  "ownership": {
    "default": 0
  },
  "_key": "!items!EKXr0UfbtMgeTumu"
}